Metadata-Version: 2.1
Name: shools
Version: 0.1.2
Summary: Basic POSIX tools in simple library.
Home-page: https://github.com/samedamci/shools
Author: samedamci
Author-email: samedamci@disroot.org
License: UNKNOWN
Project-URL: Source, https://github.com/samedamci/shools
Project-URL: Tracker, https://github.com/samedamci/shools/issues
Keywords: posix tools utils gnuutils linux shell sed
Platform: UNKNOWN
Classifier: Development Status :: 5 - Production/Stable
Classifier: Intended Audience :: Developers
Classifier: License :: OSI Approved :: ISC License (ISCL)
Classifier: Programming Language :: Python
Classifier: Programming Language :: Python :: 3
Classifier: Programming Language :: Python :: 3.6
Classifier: Programming Language :: Python :: 3.7
Classifier: Programming Language :: Python :: 3.8
Classifier: Programming Language :: Python :: 3.9
Classifier: Programming Language :: Python :: Implementation :: CPython
Classifier: Programming Language :: Python :: Implementation :: PyPy
Classifier: Topic :: Software Development :: Libraries
Classifier: Operating System :: POSIX
Classifier: Operating System :: POSIX :: BSD
Classifier: Operating System :: POSIX :: Linux
Classifier: Typing :: Typed
Requires-Python: >=3.6
License-File: LICENSE
